texttohtml/__init__.py
texttohtml/convert.py
texttohtml/elaa/__init__.py
texttohtml/elaa/io.py
texttohtml/elaa/nucleo.py
texttohtml/elaa/tags.py
texttohtml-1.0.dist-info/METADATA
texttohtml-1.0.dist-info/WHEEL
texttohtml-1.0.dist-info/top_level.txt
texttohtml-1.0.dist-info/RECORD
