Metadata-Version: 2.1
Name: texttohtml
Version: 1.0
Summary: Easy to convert text document to html document
Home-page: https://github.com/elaa0505/TexttoHtml
Author: Elango SK
Author-email: elango111000@gmail.com
License: UNKNOWN
Keywords: text2html,Text to html,Text document to html,convert text to html,Convert html using text,Texttohtml
Platform: UNKNOWN
